{
  "world_state": {
    "current_time": "22:50",
    "current_date": "2025-03-04",
    "city_name": "NYC",
    "country_name": "USA",
    "region_name": "Northeast",
    "weather_condition": "Cloudy",
    "temperature": "4\u00b0C",
    "forecast": "Cloudy overnight, clearing by morning. Low of 2\u00b0C. Sunny on Wednesday with a high of 10\u00b0C.",
    "social_climate": "Generally positive, with a sense of resilience and community spirit. Concerns remain about economic inequality and social justice.",
    "economic_condition": "Moderate growth, with some sectors thriving (tech, finance) while others struggle (retail, hospitality). Inflation is a concern.",
    "major_events": [
      "Broadway shows running at full capacity.",
      "Several tech conferences are being held this week.",
      "Local elections are upcoming next month."
    ],
    "local_news": [
      "City Council debates new affordable housing initiatives.",
      "Local hospital reports a slight increase in flu cases.",
      "Subway line experiencing delays due to signal problems."
    ],
    "transportation_status": "Subways experiencing minor delays on certain lines. Traffic is moderate for this time of night.",
    "utility_status": "All utilities (power, water, internet) are functioning normally.",
    "public_announcements": [
      "City urges residents to conserve water due to ongoing drought conditions.",
      "Reminder: Street cleaning schedule in effect.",
      "Public health officials recommend getting a flu shot."
    ],
    "trending_topics": [
      "#NYCRealEstate",
      "#TechConference",
      "#AffordableHousing",
      "#SubwayDelays"
    ],
    "current_cultural_events": [
      "Exhibition of contemporary art at the MoMA.",
      "Jazz performance at the Village Vanguard.",
      "Film festival showcasing independent movies."
    ],
    "sports_events": [
      "Knicks game at Madison Square Garden tonight.",
      "Rangers preparing for a home game later this week."
    ],
    "public_health_status": "Stable, with ongoing monitoring for seasonal illnesses. Flu cases slightly elevated.",
    "public_safety_status": "Normal, with routine police patrols. Residents advised to be aware of their surroundings."
  },
  "immediate_environment": {
    "current_location_name": "Brooklyn Roasting Company (DUMBO location)",
    "location_type": "Coffee Shop",
    "indoor_outdoor": "Indoor",
    "noise_level": "Slightly quieter for the individual using headphones, but overall moderate.",
    "lighting": "Warm, ambient lighting with some brighter task lighting over work areas.",
    "temperature_feeling": "Comfortable, slightly warm",
    "air_quality": "Good, with a slight aroma of coffee beans.",
    "present_people": [
      "Young professionals",
      "Tourists",
      "Students",
      "Locals",
      "People working on laptops"
    ],
    "crowd_density": "Moderately crowded, some tables available.",
    "social_atmosphere": "Relaxed and productive, with a mix of casual conversation and focused work.",
    "ongoing_activities": [
      "People drinking coffee and eating pastries",
      "Working on laptops",
      "Casual conversations",
      "Reading",
      "People watching"
    ],
    "nearby_objects": [
      "Coffee machines",
      "Pastry display case",
      "Tables and chairs",
      "Laptops",
      "Coffee cups",
      "Power outlets",
      "Menu boards",
      "Water dispenser",
      "Sugar and milk station",
      "Noise-canceling headphones"
    ],
    "available_services": [
      "Coffee and pastry service",
      "Free Wi-Fi",
      "Restrooms",
      "Seating",
      "Takeout",
      "Merchandise sales (coffee beans, mugs)"
    ],
    "exit_options": [
      "Front door to the street",
      "Emergency exit (clearly marked)"
    ],
    "interaction_opportunities": [
      "Ordering coffee",
      "Chatting with baristas (less likely with headphones)",
      "Overhearing conversations (much less likely with headphones)",
      "Networking with other customers (much less likely with headphones)",
      "Asking for directions"
    ],
    "visible_features": [
      "Exposed brick walls",
      "Large windows with views of the Manhattan Bridge",
      "Industrial-chic decor",
      "Coffee bean sacks",
      "Artwork on the walls",
      "Menu boards",
      "Display of coffee brewing equipment"
    ],
    "audible_sounds": [
      "Coffee grinder (fainter with headphones)",
      "Milk steamer (fainter with headphones)",
      "Conversations (fainter with headphones)",
      "Background music (indie/alternative) (fainter with headphones)",
      "Street noise (distant traffic, occasional sirens) (fainter with headphones)"
    ],
    "noticeable_smells": [
      "Freshly brewed coffee",
      "Pastries",
      "Slight hint of roasted beans"
    ],
    "seating_availability": "Some tables available, but limited.",
    "food_drink_options": [
      "Espresso drinks (lattes, cappuccinos, etc.)",
      "Brewed coffee",
      "Tea",
      "Pastries (croissants, muffins, scones)",
      "Sandwiches",
      "Salads"
    ],
    "restroom_access": "Restrooms are available for customers.",
    "recent_changes": [
      "New seasonal coffee blend introduced",
      "New pastry selection"
    ],
    "ongoing_conversations": [
      "Work-related discussions",
      "Travel plans",
      "Local news (subway delays)",
      "Tech conference buzz"
    ],
    "attention_drawing_elements": [
      "The view of the Manhattan Bridge",
      "The aroma of fresh coffee",
      "The sound of the coffee grinder (less noticeable with headphones)",
      "The activity of people working on laptops",
      "The display of coffee brewing equipment"
    ],
    "ambient_distractions": "None"
  },
  "history": [
    {
      "timestamp": "22:50",
      "date": "2025-03-04",
      "action": {
        "thought_process": "I'm feeling stressed and tired, and I need to focus on my work. The environment is distracting, but I can try to minimize the distractions. Since I had coffee recently, another cup might not be the best idea. I should try to refocus and work for another hour, then head home to get some rest. I will put on my noise cancelling headphones to block out the noise.",
        "emotional_update": "Slightly stressed and tired, but also somewhat distracted and contemplative about work-life balance.",
        "action": "Refocus on work and use noise-canceling headphones.",
        "action_details": {
          "manner": "Put on noise-canceling headphones and close unnecessary tabs on my laptop to minimize distractions. Set a timer for one hour to work on the project.",
          "duration": "60 minutes"
        },
        "updated_state": {
          "physical": "Slightly tired, had coffee 1 hour ago",
          "emotional": "Experiencing moderate stress related to work deadlines, prompting reflection on work-life balance.",
          "mental": "Focused but distracted occasionally"
        }
      }
    },
    {
      "timestamp": "22:50",
      "date": "2025-03-04",
      "action": {
        "thought_process": "Given the looming deadline and the need to focus, the best course of action is to minimize distractions and dedicate a focused block of time to coding. I'll use the headphones to further reduce noise and set a timer to work uninterrupted for a specific duration. After that, I'll take a short break to stretch and refocus before resuming.",
        "emotional_update": "The character is experiencing moderate stress related to work, coupled with a reflective mood concerning their career and work-life balance.",
        "action": "Focus on coding for a set period.",
        "action_details": {
          "manner": null,
          "duration": "90 minutes"
        },
        "updated_state": {
          "physical": "Slightly tired, had coffee 1 hour ago",
          "emotional": "Experiencing moderate stress related to work deadlines, prompting reflection on work-life balance.",
          "mental": "Focused but distracted occasionally"
        }
      }
    },
    {
      "timestamp": "22:50",
      "date": "2025-03-04",
      "action": {
        "thought_process": "Given the stress and the need to complete the project, the best course of action is to focus on the code for a set period. I'll use the timer to ensure I take a break afterward to address the work-life balance concerns later. Continuing to work in the coffee shop is acceptable since the headphones are mitigating the noise.",
        "emotional_update": "Experiencing moderate stress related to work deadlines, prompting reflection on work-life balance.",
        "action": "Continue working on the code",
        "action_details": {
          "manner": null,
          "duration": "Focus intensely for the next 45 minutes, then take a 15-minute break."
        },
        "updated_state": {
          "physical": "Slightly tired, had coffee 1 hour ago",
          "emotional": "Experiencing moderate stress related to work deadlines, prompting reflection on work-life balance.",
          "mental": "Focused but distracted occasionally"
        }
      }
    },
    {
      "timestamp": "22:50",
      "date": "2025-03-04",
      "action": {
        "thought_process": "Given the looming deadline and my desire to make progress, I need to refocus and work efficiently. However, I also need to acknowledge my stress and the importance of work-life balance. A short break to appreciate the view and recharge before diving back in seems like a good compromise.",
        "emotional_update": "Experiencing moderate stress related to a deadline, but also expressing a desire for work-life balance and a hopeful outlook for a break after completing the task.",
        "action": "Take a short break to appreciate the view and mentally reset before continuing work.",
        "action_details": {
          "manner": null,
          "duration": "5 minutes"
        },
        "updated_state": {
          "physical": "Slightly tired, had coffee 1 hour ago",
          "emotional": "Experiencing work-related stress, but also hopeful for improved work-life balance.",
          "mental": "Focused but distracted occasionally"
        }
      }
    },
    {
      "timestamp": "22:50",
      "date": "2025-03-04",
      "action": {
        "thought_process": "I've had a sufficient break and the deadline is looming. While the view is nice, I need to prioritize completing the project. Lingering longer will only increase my stress later. Time to get back to work.",
        "emotional_update": "Experiencing moderate stress related to work, but also hopeful for a future break and better work-life balance.",
        "action": "Return to work",
        "action_details": {
          "manner": "Focused",
          "duration": "Until project completion"
        },
        "updated_state": {
          "physical": "Slightly tired, had coffee 1 hour ago",
          "emotional": "Experiencing work-related stress, but also hopeful for improved work-life balance.",
          "mental": "Focused but distracted occasionally"
        }
      }
    },
    {
      "timestamp": "22:50",
      "date": "2025-03-04",
      "action": {
        "thought_process": "Given my stress and the need to meet the deadline, I need to refocus and power through. Taking a short, structured break might help me return to the task with renewed energy. I'll use a timer to ensure the break doesn't turn into procrastination.",
        "emotional_update": "Experiencing work-related stress, but also hopeful for improved work-life balance.",
        "action": "Take a short break to stretch and clear my head.",
        "action_details": {
          "manner": null,
          "duration": "5 minutes"
        },
        "updated_state": {
          "physical": "Slightly tired, had coffee 1 hour ago",
          "emotional": "Experiencing work-related stress, but also hopeful for improved work-life balance.",
          "mental": "Focused but distracted occasionally"
        }
      }
    }
  ],
  "reaction_profile": {
    "consequence_severity": "moderate",
    "social_responsiveness": "neutral",
    "environmental_stability": "dynamic",
    "coincidence_frequency": "occasional",
    "challenge_level": "normal",
    "narrative_tone": "mundane",
    "opportunity_frequency": "normal",
    "serendipity": "medium",
    "world_awareness": "normal",
    "karmic_response": "moderate"
  }
}