{
  "world_instance_uuid": "1fedc5fe-945e-4911-9406-0c013c67df4c",
  "world_type": "real",
  "sub_genre": "realtime",
  "description": "A simulation mirroring the current real world in New York, New York. Standard physics apply.",
  "rules": {
    "allow_teleportation": false,
    "time_progression_rate": 1.0,
    "weather_effects_travel": true,
    "historical_date": null
  },
  "location": {
    "city": "New York",
    "state": null,
    "country": "New York"
  },
  "setup_timestamp_utc": "2025-05-20T15:56:51.936259+00:00Z"
}